Workbook

Sheet Monthly Projections
A1: ALDER & ASH DIGITAL — Year 1 Monthly Projections (2026)
A3: Metric | B3: Jan-26 | C3: Feb-26 | D3: Mar-26 | E3: Apr-26 | F3: May-26 | G3: Jun-26 | H3: Jul-26 | I3: Aug-26 | J3: Sep-26 | K3: Oct-26 | L3: Nov-26 | M3: Dec-26 | N3: FY 2026
A4: ── REVENUE ──
A5: Website Projects Closed | B5: 1 | C5: 1 | D5: 1 | E5: 2 | F5: 2 | G5: 3 | H5: 3 | I5: 3 | J5: 3 | K5: 3 | L5: 3 | M5: 3 | N5: =SUM(B5:M5)
A6: Avg Project Value ($) | B6: 3500 | C6: 3500 | D6: 3500 | E6: 3500 | F6: 3500 | G6: 3500 | H6: 3500 | I6: 3500 | J6: 3500 | K6: 3500 | L6: 3500 | M6: 3500 | N6: =AVERAGE(B6:M6)
A7: Project Revenue | B7: =B5*B6 | C7: =C5*C6 | D7: =D5*D6 | E7: =E5*E6 | F7: =F5*F6 | G7: =G5*G6 | H7: =H5*H6 | I7: =I5*I6 | ... M7: =M5*M6 | N7: =SUM(B7:M7)
A8: New Retainer Clients | B8: =B5 | C8: =C5 | D8: =D5 | E8: =E5 | F8: =F5 | G8: =G5 | H8: =H5 | I8: =I5 | ... M8: =M5 | N8: =SUM(B8:M8)
A9: Cumulative Retainers | B9: =B8 | C9: =B9+C8 | D9: =C9+D8 | E9: =D9+E8 | F9: =E9+F8 | G9: =F9+G8 | H9: =G9+H8 | I9: =H9+I8 | J9: =I9+J8 | ... M9: =L9+M8 | N9: =M9
A10: Retainer Rate ($/mo) | B10: 250 | C10: 250 | D10: 250 | E10: 250 | F10: 250 | G10: 250 | H10: 250 | I10: 250 | J10: 250 | K10: 250 | L10: 250 | M10: 250 | N10: =AVERAGE(B10:M10)
A11: Retainer Revenue | B11: =B9*B10 | C11: =C9*C10 | D11: =D9*D10 | E11: =E9*E10 | F11: =F9*F10 | G11: =G9*G10 | H11: =H9*H10 | I11: =I9*I10 | ... M11: =M9*M10 | N11: =SUM(B11:M11)
A12: Add-On Revenue (30%) | B12: =B7*0.3 | C12: =C7*0.3 | D12: =D7*0.3 | E12: =E7*0.3 | F12: =F7*0.3 | G12: =G7*0.3 | H12: =H7*0.3 | I12: =I7*0.3 | ... M12: =M7*0.3 | N12: =SUM(B12:M12)
A13: TOTAL MONTHLY REVENUE | B13: =B7+B11+B12 | C13: =C7+C11+C12 | D13: =D7+D11+D12 | E13: =E7+E11+E12 | F13: =F7+F11+F12 | G13: =G7+G11+G12 | H13: =H7+H11+H12 | I13: =I7+I11+I12 | ... M13: =M7+M11+M12 | N13: =SUM(B13:M13)
A14: ── EXPENSES ──
A15: Software & Tools | B15: 200 | C15: 200 | D15: 200 | E15: 200 | F15: 200 | G15: 200 | H15: 200 | I15: 200 | J15: 200 | K15: 200 | L15: 200 | M15: 200 | N15: =SUM(B15:M15)
A16: Marketing | B16: 300 | C16: 300 | D16: 300 | E16: 300 | F16: 300 | G16: 300 | H16: 300 | I16: 300 | J16: 300 | K16: 300 | L16: 300 | M16: 300 | N16: =SUM(B16:M16)
A17: Insurance | B17: 100 | C17: 100 | D17: 100 | E17: 100 | F17: 100 | G17: 100 | H17: 100 | I17: 100 | J17: 100 | K17: 100 | L17: 100 | M17: 100 | N17: =SUM(B17:M17)
A18: Miscellaneous | B18: 150 | C18: 150 | D18: 150 | E18: 150 | F18: 150 | G18: 150 | H18: 150 | I18: 150 | J18: 150 | K18: 150 | L18: 150 | M18: 150 | N18: =SUM(B18:M18)
A19: TOTAL EXPENSES | B19: =SUM(B15:B18) | C19: =SUM(C15:C18) | D19: =SUM(D15:D18) | E19: =SUM(E15:E18) | F19: =SUM(F15:F18) | G19: =SUM(G15:G18) | H19: =SUM(H15:H18) | I19: =SUM(I15:I18) | ... M19: =SUM(M15:M18) | N19: =SUM(B19:M19)
A20: ── PROFIT ──
A21: NET PROFIT | B21: =B13-B19 | C21: =C13-C19 | D21: =D13-D19 | E21: =E13-E19 | F21: =F13-F19 | G21: =G13-G19 | H21: =H13-H19 | I21: =I13-I19 | ... M21: =M13-M19 | N21: =SUM(B21:M21)
A22: CUMULATIVE REVENUE | B22: =B13 | C22: =B22+C13 | D22: =C22+D13 | E22: =D22+E13 | F22: =E22+F13 | G22: =F22+G13 | H22: =G22+H13 | I22: =H22+I13 | J22: =I22+J13 | ... M22: =L22+M13 | N22: =M22
A23: PROFIT MARGIN | B23: =IF(B13=0,0,B21/B13) | C23: =IF(C13=0,0,C21/C13) | D23: =IF(D13=0,0,D21/D13) | E23: =IF(E13=0,0,E21/E13) | F23: =IF(F13=0,0,F21/F13) | G23: =IF(G13=0,0,G21/G13) | H23: =IF(H13=0,0,H21/H13) | I23: =IF(I13=0,0,I21/I13) | ... N23: =IF(N13=0,0,N21/N13)
A24: Source: Internal projections, Alder & Ash Digital business plan. Blue cells = inputs (editable). All calculations via Excel formulas.

Sheet Annual Summary
A1: ALDER & ASH DIGITAL — Annual Summary
A3: Metric | B3: Year 1 (2026) | C3: Year 2 (2027) | D3: YoY Change
A4: ── REVENUE METRICS ──
A5: Total Revenue ($) | B5: ='Monthly Projections'!N13 | C5: 185000 | D5: =IF(B5=0,0,(C5-B5)/B5)
A6: Total Expenses ($) | B6: ='Monthly Projections'!N19 | C6: 18000 | D6: =IF(B6=0,0,(C6-B6)/B6)
A7: Net Profit ($) | B7: =B5-B6 | C7: =C5-C6 | D7: =IF(B7=0,0,(C7-B7)/B7)
A8: Profit Margin (%) | B8: =IF(B5=0,0,B7/B5) | C8: =IF(C5=0,0,C7/C5) | D8: =IF(B8=0,0,C8-B8)
A9: ── VOLUME METRICS ──
A10: Projects Completed | B10: ='Monthly Projections'!N5 | C10: 42 | D10: =IF(B10=0,0,(C10-B10)/B10)
A11: Avg Projects/Month | B11: ='Monthly Projections'!N5/12 | C11: 3.5 | D11: =IF(B11=0,0,(C11-B11)/B11)
A12: End-of-Year Retainers | B12: ='Monthly Projections'!N9 | C12: 28 | D12: =IF(B12=0,0,(C12-B12)/B12)
A13: ── MRR & GROWTH ──
A14: MRR from Retainers (Dec) | B14: ='Monthly Projections'!M11 | C14: 7000 | D14: =IF(B14=0,0,(C14-B14)/B14)
A15: Avg Monthly Revenue | B15: =B5/12 | C15: =C5/12 | D15: =IF(B15=0,0,(C15-B15)/B15)
A16: Avg Monthly Expenses | B16: =B6/12 | C16: =C6/12 | D16: =IF(B16=0,0,(C16-B16)/B16)
A17: ── YEAR 2 ASSUMPTIONS ──
A18: Target Sites/Month (avg) | C18: 3.5 | D18: =IF(B18=0,0,(C18-B18)/B18)
A19: Target Retainers (EoY) | C19: 28 | D19: =IF(B19=0,0,(C19-B19)/B19)
A20: Avg Project Value ($) | C20: 4000 | D20: =IF(B20=0,0,(C20-B20)/B20)
A21: Retainer Rate ($/mo) | C21: 275 | D21: =IF(B21=0,0,(C21-B21)/B21)
A22: Year 2 figures are management estimates. Blue cells = editable inputs. Green cells = linked from Monthly Projections sheet.

Sheet Pricing Calculator
A1: ALDER & ASH DIGITAL — Pricing Calculator
A3: INPUTS — Edit Blue Cells
A4: Project Price ($) | B4: 5000
A5: Retainer Price ($/mo) | B5: 250
A6: Projects per Month | B6: 2
A7: Client Retention Rate (%) | B7: 0.75
A8: Add-On % of Project Rev | B8: 0.3
A9: Monthly Fixed Expenses ($) | B9: 750
A11: PROJECTED OUTPUTS
A12: Monthly Breakdown
A13: Monthly Project Revenue | B13: =B6*B4
A14: Monthly Retainer Revenue | B14: =B6*B7*B5
A15: Monthly Add-On Revenue | B15: =B13*B8
A16: Total Monthly Revenue | B16: =B13+B14+B15
A17: Total Monthly Expenses | B17: =B9
A18: Monthly Net Profit | B18: =B16-B17
A19: Monthly Profit Margin | B19: =IF(B16=0,0,B18/B16)
A21: Annual Projection
A22: Annual Project Revenue | B22: =B13*12
A23: Annual Retainer Revenue | B23: =B14*12
A24: Annual Add-On Revenue | B24: =B15*12
A25: Total Annual Revenue | B25: =B16*12
A26: Total Annual Expenses | B26: =B17*12
A27: Annual Net Profit | B27: =B25-B26
A28: Annual Profit Margin | B28: =IF(B25=0,0,B27/B25)
A30: Break-Even Analysis
A31: Monthly Fixed Costs | B31: =B9
A32: Revenue per Project | B32: =B4*(1+B8)
A33: Break-Even Projects/Month | B33: =IF(B32=0,0,B31/B32)
A34: Break-Even Revenue/Month | B34: =B31
A35: Safety Margin | B35: =IF(B16=0,0,(B16-B31)/B16)
A37: Blue cells = inputs. Green cells = break-even outputs. All outputs recalculate automatically when inputs change.
